[{"name":"python node java","path":"api/tags/python-node-java.json","slug":"python-node-java","count":1},{"name":"docker","path":"api/tags/docker.json","slug":"docker","count":2},{"name":"kafka","path":"api/tags/kafka.json","slug":"kafka","count":2},{"name":"zookeeper","path":"api/tags/zookeeper.json","slug":"zookeeper","count":1},{"name":"Nginx","path":"api/tags/Nginx.json","slug":"Nginx","count":2},{"name":"springboot","path":"api/tags/springboot.json","slug":"springboot","count":1},{"name":"Java高并发","path":"api/tags/Java高并发.json","slug":"Java高并发","count":1},{"name":"JUC","path":"api/tags/JUC.json","slug":"JUC","count":1},{"name":"英语","path":"api/tags/英语.json","slug":"英语","count":1},{"name":"考研政治","path":"api/tags/考研政治.json","slug":"考研政治","count":4},{"name":"Mysql","path":"api/tags/Mysql.json","slug":"Mysql","count":1},{"name":"Node Node基础系列","path":"api/tags/Node-Node基础系列.json","slug":"Node-Node基础系列","count":12}]